pysilero_vad/__init__.py
pysilero_vad/ggml-silero-v6.2.0.bin
pysilero_vad/py.typed
pysilero_vad/silero_vad.abi3.so
pysilero_vad-3.2.0.dist-info/METADATA
pysilero_vad-3.2.0.dist-info/WHEEL
pysilero_vad-3.2.0.dist-info/top_level.txt
pysilero_vad-3.2.0.dist-info/RECORD
pysilero_vad-3.2.0.dist-info/licenses/LICENSE.md
